interrogatio/__init__.py
interrogatio/core/__init__.py
interrogatio/core/dialog.py
interrogatio/core/exceptions.py
interrogatio/core/prompt.py
interrogatio/core/utils.py
interrogatio/handlers/__init__.py
interrogatio/handlers/base.py
interrogatio/handlers/builtins.py
interrogatio/handlers/registry.py
interrogatio/main.py
interrogatio/shortcuts/__init__.py
interrogatio/shortcuts/dialogs.py
interrogatio/themes/__init__.py
interrogatio/themes/base.py
interrogatio/themes/builtins.py
interrogatio/themes/theme_files/default.json
interrogatio/themes/theme_files/purple.json
interrogatio/validators/__init__.py
interrogatio/validators/base.py
interrogatio/validators/builtins.py
interrogatio/validators/registry.py
interrogatio/widgets/__init__.py
interrogatio/widgets/base.py
interrogatio/widgets/wizard.py
interrogatio-2.4.0.dist-info/LICENSE
interrogatio-2.4.0.dist-info/METADATA
interrogatio-2.4.0.dist-info/WHEEL
interrogatio-2.4.0.dist-info/entry_points.txt
interrogatio-2.4.0.dist-info/RECORD
