Metadata-Version: 2.1
Name: interrogatio
Version: 2.4.0
Summary: Prompting library for terminals.
Home-page: https://github.com/ffaraone/interrogatio
License: BSD-3-Clause
Author: Francesco Faraone
Requires-Python: >=3.8,<4
Classifier: Development Status :: 5 - Production/Stable
Classifier: Environment :: Console
Classifier: Intended Audience :: Developers
Classifier: License :: OSI Approved :: BSD License
Classifier: Operating System :: OS Independent
Classifier: Programming Language :: Python :: 3
Classifier: Programming Language :: Python :: 3.8
Classifier: Programming Language :: Python :: 3.9
Classifier: Programming Language :: Python :: 3.10
Classifier: Programming Language :: Python :: 3.11
Classifier: Programming Language :: Python :: 3.12
Classifier: Programming Language :: Python :: 3.13
Classifier: Topic :: Software Development :: Libraries
Classifier: Topic :: Utilities
Provides-Extra: yaml
Requires-Dist: PyYAML (>=5) ; extra == "yaml"
Requires-Dist: importlib-metadata (>=8.5.0,<9.0.0)
Requires-Dist: prompt-toolkit (>=3.0.29)
Requires-Dist: pytz (>=2022.1,<2023.0)
Requires-Dist: tzlocal (>=4.1,<5.0)
Requires-Dist: validators (>=0.18.2,<0.19.0)
Project-URL: Documentation, https://interrogatio.readthedocs.io/en/latest/
Project-URL: Repository, https://github.com/ffaraone/interrogatio.git
